AutoChrome/__init__.py
AutoChrome/auto_chrome.py
AutoChrome/utils/__init__.py
AutoChrome/utils/auto_chrome_cli.py
AutoChrome/utils/chrome_downloader.py
AutoChrome/utils/custom_types.py
AutoChrome/utils/errors.py
AutoChrome/utils/logger.py
autochrome-0.1.10.dist-info/entry_points.txt
autochrome-0.1.10.dist-info/LICENSE
autochrome-0.1.10.dist-info/METADATA
autochrome-0.1.10.dist-info/WHEEL
autochrome-0.1.10.dist-info/RECORD
