Metadata-Version: 2.3
Name: AutoChrome
Version: 0.1.10
Summary: 基于 DrissionPage 封装的自用API，用于网页自动化。
Author: Xiaoqiang
Author-email: xiaoqiangclub@hotmail.com
Requires-Python: >=3.10
Classifier: Programming Language :: Python :: 3
Classifier: Programming Language :: Python :: 3.10
Classifier: Programming Language :: Python :: 3.11
Classifier: Programming Language :: Python :: 3.12
Classifier: Programming Language :: Python :: 3.13
Requires-Dist: drissionpage (>=4.1.0.18,<5.0.0.0)
Requires-Dist: pypiwin32 (>=223,<224) ; sys_platform == "win32"
Requires-Dist: tqdm (>=4.67.1,<5.0.0)
